[
  {
    "inputs": [
      {
        "internalType": "address",
        "name": "",
        "type": "address"
      }
    ],
    "name": "ZeroAddress",
    "type": "error"
  },
  {
    "inputs": [
      {
        "internalType": "uint256",
        "name": "unit",
        "type": "uint256"
      }
    ],
    "name": "createBank",
    "outputs": [
      {
        "internalType": "address",
        "name": "bank",
        "type": "address"
      }
    ],
    "stateMutability": "nonpayable",
    "type": "function"
  },
  {
    "inputs": [
      {
        "internalType": "uint256",
        "name": "unit",
        "type": "uint256"
      }
    ],
    "name": "getBank",
    "outputs": [
      {
        "internalType": "address",
        "name": "",
        "type": "address"
      }
    ],
    "stateMutability": "view",
    "type": "function"
  }
]